MANIFEST.in
README.rst
setup.py
tree2ogg
tree2ogg/__init__.py
tree2ogg/__main__.py
tree2ogg/subprocess_pool.py
tree2ogg.egg-info/PKG-INFO
tree2ogg.egg-info/SOURCES.txt
tree2ogg.egg-info/dependency_links.txt
tree2ogg.egg-info/entry_points.txt
tree2ogg.egg-info/top_level.txt