Metadata-Version: 1.1
Name: tree2ogg
Version: 0.2.0
Summary: A script that allows recursively transcode directories/playlists of FLAC files to Ogg.
Home-page: https://github.com/guyru/tree2ogg/
Author: Guy Rutenberg
Author-email: guyrutenberg@gmail.com
License: GPLv2+
Platform: UNKNOWN
Classifier: Environment :: Console
Classifier: Intended Audience :: End Users/Desktop
Classifier: License :: OSI Approved :: GNU General Public License v2 or later (GPLv2+)
Classifier: Development Status :: 4 - Beta
